nvidia_stub/ERROR.txt
nvidia_stub/__about__.py
nvidia_stub/__init__.py
nvidia_stub/buildapi.py
nvidia_stub/common.py
nvidia_stub/error.py
nvidia_stub/sdist.py
nvidia_stub/wheel.py
nvidia_stub/_vendor/README.md
nvidia_stub/_vendor/__init__.py
nvidia_stub/_vendor/packaging/LICENSE
nvidia_stub/_vendor/packaging/__init__.py
nvidia_stub/_vendor/packaging/_elffile.py
nvidia_stub/_vendor/packaging/_manylinux.py
nvidia_stub/_vendor/packaging/_musllinux.py
nvidia_stub/_vendor/packaging/_parser.py
nvidia_stub/_vendor/packaging/_structures.py
nvidia_stub/_vendor/packaging/_tokenizer.py
nvidia_stub/_vendor/packaging/markers.py
nvidia_stub/_vendor/packaging/metadata.py
nvidia_stub/_vendor/packaging/py.typed
nvidia_stub/_vendor/packaging/requirements.py
nvidia_stub/_vendor/packaging/specifiers.py
nvidia_stub/_vendor/packaging/tags.py
nvidia_stub/_vendor/packaging/utils.py
nvidia_stub/_vendor/packaging/version.py
nvidia_stub-0.1.8.dist-info/METADATA
nvidia_stub-0.1.8.dist-info/WHEEL
nvidia_stub-0.1.8.dist-info/licenses/LICENSE
nvidia_stub-0.1.8.dist-info/RECORD
